AUTHORS
LICENSE
MANIFEST.in
README.rst
setup.py
healthcare/__init__.py
healthcare/api.py
healthcare/exceptions.py
healthcare/models.py
healthcare/views.py
healthcare/backends/__init__.py
healthcare/backends/base.py
healthcare/backends/comparisons.py
healthcare/backends/dummy.py
healthcare/backends/djhealth/__init__.py
healthcare/backends/djhealth/models.py
healthcare/backends/djhealth/storage.py
healthcare/backends/djhealth/migrations/0001_initial.py
healthcare/backends/djhealth/migrations/__init__.py
healthcare/tests/__init__.py
healthcare/tests/test_api.py
healthcare/tests/backends/__init__.py
healthcare/tests/backends/base.py
healthcare/tests/backends/test_django.py
healthcare/tests/backends/test_dummy.py
rapidsms_healthcare.egg-info/PKG-INFO
rapidsms_healthcare.egg-info/SOURCES.txt
rapidsms_healthcare.egg-info/dependency_links.txt
rapidsms_healthcare.egg-info/not-zip-safe
rapidsms_healthcare.egg-info/top_level.txt